<?xml version="1.0" encoding="utf-8"?>
<?zms version='ZMS5-5.1.0'?>
<list>
  <item type="dictionary">
    <dictionary>
      <item key="eng">Restore</item>
      <item key="fra">Restaurer</item>
      <item key="ger">Zurücksetzen</item>
      <item key="key">zms.formulator.lib.BUTTON_RESTORE</item>
    </dictionary>
  </item>
  <item type="dictionary">
    <dictionary>
      <item key="eng">Submit</item>
      <item key="fra">Soumettre</item>
      <item key="ger">Absenden</item>
      <item key="key">zms.formulator.lib.BUTTON_SUBMIT</item>
    </dictionary>
  </item>
  <item type="dictionary">
    <dictionary>
      <item key="eng">No additional items allowed in this array</item>
      <item key="fra">No additional items allowed in this array</item>
      <item key="ger">Keine weiteren Elemente in diesem Array erlaubt!</item>
      <item key="key">zms.formulator.lib.ERROR_ADDITIONALITEMS</item>
    </dictionary>
  </item>
  <item type="dictionary">
    <dictionary>
      <item key="eng">No additional properties allowed, but property {{0}} is set</item>
      <item key="fra">No additional properties allowed, but property {{0}} is set</item>
      <item key="ger">Keine weiteren Eigenschaften sind erlaubt; die Eigenschaft {{0}} ist gesetzt</item>
      <item key="key">zms.formulator.lib.ERROR_ADDITIONAL_PROPERTIES</item>
    </dictionary>
  </item>
  <item type="dictionary">
    <dictionary>
      <item key="eng">Value must validate against at least one of the provided schemas</item>
      <item key="fra">Value must validate against at least one of the provided schemas</item>
      <item key="ger">Value must validate against at least one of the provided schemas</item>
      <item key="key">zms.formulator.lib.ERROR_ANYOF</item>
    </dictionary>
  </item>
  <item type="dictionary">
    <dictionary>
      <item key="eng">Must have property {{0}}</item>
      <item key="fra">Must have property {{0}}</item>
      <item key="ger">Muss die Eigenschaft {{0}} haben</item>
      <item key="key">zms.formulator.lib.ERROR_DEPENDENCY</item>
    </dictionary>
  </item>
  <item type="dictionary">
    <dictionary>
      <item key="eng">Value must not be of type {{0}}</item>
      <item key="fra">Value must not be of type {{0}}</item>
      <item key="ger">Der Wert darf nicht dem Typen {{0}} entsprechen</item>
      <item key="key">zms.formulator.lib.ERROR_DISALLOW</item>
    </dictionary>
  </item>
  <item type="dictionary">
    <dictionary>
      <item key="eng">Value must not be one of the provided disallowed types</item>
      <item key="fra">Value must not be one of the provided disallowed types</item>
      <item key="ger">Der Wert darf nicht einem der unerlaubten Typen entsprechen</item>
      <item key="key">zms.formulator.lib.ERROR_DISALLOW_UNION</item>
    </dictionary>
  </item>
  <item type="dictionary">
    <dictionary>
      <item key="eng">Value must be one of the enumerated values</item>
      <item key="fra">Value must be one of the enumerated values</item>
      <item key="ger">Der Wert muss einem der aufgezählten Werte entsprechen</item>
      <item key="key">zms.formulator.lib.ERROR_ENUM</item>
    </dictionary>
  </item>
  <item type="dictionary">
    <dictionary>
      <item key="eng">Value is mandatory</item>
      <item key="fra">Value is mandatory</item>
      <item key="ger">Der Wert ist eine Pflichtangabe</item>
      <item key="key">zms.formulator.lib.ERROR_MANDATORY</item>
    </dictionary>
  </item>
  <item type="dictionary">
    <dictionary>
      <item key="eng">Value must be less than {{0}}</item>
      <item key="fra">Value must be less than {{0}}</item>
      <item key="ger">Der Wert muss kleiner sein als {{0}}</item>
      <item key="key">zms.formulator.lib.ERROR_MAXIMUM_EXCL</item>
    </dictionary>
  </item>
  <item type="dictionary">
    <dictionary>
      <item key="eng">Value must be at most {{0}}</item>
      <item key="fra">Value must be at most {{0}}</item>
      <item key="ger">Der Wert muss maximal {{0}} sein</item>
      <item key="key">zms.formulator.lib.ERROR_MAXIMUM_INCL</item>
    </dictionary>
  </item>
  <item type="dictionary">
    <dictionary>
      <item key="eng">Value must have at most {{0}} items</item>
      <item key="fra">Value must have at most {{0}} items</item>
      <item key="ger">Der Wert darf maximal {{0}} Elemente enthalten</item>
      <item key="key">zms.formulator.lib.ERROR_MAXITEMS</item>
    </dictionary>
  </item>
  <item type="dictionary">
    <dictionary>
      <item key="eng">Value must be at most {{0}} characters long</item>
      <item key="fra">Value must be at most {{0}} characters long</item>
      <item key="ger">Der Wert darf maximal {{0}} Zeichen lang sein</item>
      <item key="key">zms.formulator.lib.ERROR_MAXLENGTH</item>
    </dictionary>
  </item>
  <item type="dictionary">
    <dictionary>
      <item key="eng">Object must have at most {{0}} properties</item>
      <item key="fra">Object must have at most {{0}} properties</item>
      <item key="ger">Das Objekt darf maximal {{0}} Eigenschaften haben</item>
      <item key="key">zms.formulator.lib.ERROR_MAXPROPERTIES</item>
    </dictionary>
  </item>
  <item type="dictionary">
    <dictionary>
      <item key="eng">Value must be greater than {{0}}</item>
      <item key="fra">Value must be greater than {{0}}</item>
      <item key="ger">Der Wert muss grösser sein als {{0}}</item>
      <item key="key">zms.formulator.lib.ERROR_MINIMUM_EXCL</item>
    </dictionary>
  </item>
  <item type="dictionary">
    <dictionary>
      <item key="eng">Value must be at least {{0}}</item>
      <item key="fra">Value must be at least {{0}}</item>
      <item key="ger">Der Wert muss mindestens {{0}} sein</item>
      <item key="key">zms.formulator.lib.ERROR_MINIMUM_INCL</item>
    </dictionary>
  </item>
  <item type="dictionary">
    <dictionary>
      <item key="eng">Value must have at least {{0}} items</item>
      <item key="fra">Value must have at least {{0}} items</item>
      <item key="ger">Der Wert muss mindestens {{0}} Elemente enthalten</item>
      <item key="key">zms.formulator.lib.ERROR_MINITEMS</item>
    </dictionary>
  </item>
  <item type="dictionary">
    <dictionary>
      <item key="eng">Value must be at least {{0}} characters long</item>
      <item key="fra">Value must be at least {{0}} characters long</item>
      <item key="ger">Der Wert muss mindestens {{0}} Zeichen lang sein</item>
      <item key="key">zms.formulator.lib.ERROR_MINLENGTH</item>
    </dictionary>
  </item>
  <item type="dictionary">
    <dictionary>
      <item key="eng">Object must have at least {{0}} properties</item>
      <item key="fra">Object must have at least {{0}} properties</item>
      <item key="ger">Das Objekt muss mindestens {{0}} Eigenschaften haben</item>
      <item key="key">zms.formulator.lib.ERROR_MINPROPERTIES</item>
    </dictionary>
  </item>
  <item type="dictionary">
    <dictionary>
      <item key="eng">Value must be a multiple of {{0}}</item>
      <item key="fra">Value must be a multiple of {{0}}</item>
      <item key="ger">Der Wert muss ein Vielfaches von {{0}} sein</item>
      <item key="key">zms.formulator.lib.ERROR_MULTIPLEOF</item>
    </dictionary>
  </item>
  <item type="dictionary">
    <dictionary>
      <item key="eng">Value must not validate against the provided schema</item>
      <item key="fra">Value must not validate against the provided schema</item>
      <item key="ger">Value must not validate against the provided schema</item>
      <item key="key">zms.formulator.lib.ERROR_NOT</item>
    </dictionary>
  </item>
  <item type="dictionary">
    <dictionary>
      <item key="eng">Value required</item>
      <item key="fra">Value required</item>
      <item key="ger">Es wird ein Wert benötigt</item>
      <item key="key">zms.formulator.lib.ERROR_NOTEMPTY</item>
    </dictionary>
  </item>
  <item type="dictionary">
    <dictionary>
      <item key="eng">Property must be set</item>
      <item key="fra">Property must be set</item>
      <item key="ger">Eigenschaft muss angegeben werden</item>
      <item key="key">zms.formulator.lib.ERROR_NOTSET</item>
    </dictionary>
  </item>
  <item type="dictionary">
    <dictionary>
      <item key="eng">Value must validate against exactly one of the provided schemas. It currently validates against {{0}} of the schemas.</item>
      <item key="fra">Value must validate against exactly one of the provided schemas. It currently validates against {{0}} of the schemas.</item>
      <item key="ger">Value must validate against exactly one of the provided schemas. It currently validates against {{0}} of the schemas.</item>
      <item key="key">zms.formulator.lib.ERROR_ONEOF</item>
    </dictionary>
  </item>
  <item type="dictionary">
    <dictionary>
      <item key="eng">Value must match the provided pattern</item>
      <item key="fra">Value must match the provided pattern</item>
      <item key="ger">Der Wert muss dem vorgegebenen Muster entsprechen</item>
      <item key="key">zms.formulator.lib.ERROR_PATTERN</item>
    </dictionary>
  </item>
  <item type="dictionary">
    <dictionary>
      <item key="eng">Object is missing the required property '{{0}}'</item>
      <item key="fra">Object is missing the required property '{{0}}'</item>
      <item key="ger">Dem Objekt fehlt die benötigte Eigenschaft '{{0}}'</item>
      <item key="key">zms.formulator.lib.ERROR_REQUIRED</item>
    </dictionary>
  </item>
  <item type="dictionary">
    <dictionary>
      <item key="eng">Value must be of type {{0}}</item>
      <item key="fra">Value must be of type {{0}}</item>
      <item key="ger">Der Wert muss dem Typen {{0}} entsprechen</item>
      <item key="key">zms.formulator.lib.ERROR_TYPE</item>
    </dictionary>
  </item>
  <item type="dictionary">
    <dictionary>
      <item key="eng">Value must be one of the provided types</item>
      <item key="fra">Value must be one of the provided types</item>
      <item key="ger">Der Wert muss dem vorgegebenen Typen entsprechen</item>
      <item key="key">zms.formulator.lib.ERROR_TYPE_UNION</item>
    </dictionary>
  </item>
  <item type="dictionary">
    <dictionary>
      <item key="eng">Array must have unique items</item>
      <item key="fra">Array must have unique items</item>
      <item key="ger">Das Feld darf nur eindeutige Elemente enthalten!</item>
      <item key="key">zms.formulator.lib.ERROR_UNIQUEITEMS</item>
    </dictionary>
  </item>
  <item type="dictionary">
    <dictionary>
      <item key="eng">Thank you, we have received the data.</item>
      <item key="fra">Thank you, we have received the data.</item>
      <item key="ger">Vielen Dank, die Daten sind bei uns eingegangen.</item>
      <item key="key">zms.formulator.lib.FEEDBACK_MSG</item>
    </dictionary>
  </item>
  <item type="dictionary">
    <dictionary>
      <item key="eng">Please check your input!</item>
      <item key="fra">Please check your input!</item>
      <item key="ger">Bitte überprüfen Sie Ihre Eingabe!</item>
      <item key="key">zms.formulator.lib.HINT_CHECKINPUT</item>
    </dictionary>
  </item>
  <item type="dictionary">
    <dictionary>
      <item key="eng">Data was not sent. Are you a robot?</item>
      <item key="fra">Data was not sent. Are you a robot?</item>
      <item key="ger">Daten wurden nicht übertragen! Bist du etwa ein Roboter?</item>
      <item key="key">zms.formulator.lib.HINT_DATANOTSENT</item>
    </dictionary>
  </item>
  <item type="dictionary">
    <dictionary>
      <item key="eng">Data was sent.</item>
      <item key="fra">Data was sent.</item>
      <item key="ger">Die Daten wurden übertragen.</item>
      <item key="key">zms.formulator.lib.HINT_DATASENT</item>
    </dictionary>
  </item>
  <item type="dictionary">
    <dictionary>
      <item key="eng">E-Mails expect a format like \"user@domain.tld\"</item>
      <item key="fra">E-Mails expect a format like \"user@domain.tld\"</item>
      <item key="ger">E-Mails erwarten ein Format wie \"user@domain.tld\"</item>
      <item key="key">zms.formulator.lib.HINT_EMAILSYNTAX</item>
    </dictionary>
  </item>
  <item type="dictionary">
    <dictionary>
      <item key="eng">An Error occurred!</item>
      <item key="fra">An Error occurred!</item>
      <item key="ger">Es ist ein Fehler aufgetreten!</item>
      <item key="key">zms.formulator.lib.HINT_ERROROCCURED</item>
    </dictionary>
  </item>
  <item type="dictionary">
    <dictionary>
      <item key="eng">File size:</item>
      <item key="fra">File size:</item>
      <item key="ger">Dateigröße:</item>
      <item key="key">zms.formulator.lib.HINT_FILESIZE</item>
    </dictionary>
  </item>
  <item type="dictionary">
    <dictionary>
      <item key="eng">File type:</item>
      <item key="fra">File type:</item>
      <item key="ger">Dateityp:</item>
      <item key="key">zms.formulator.lib.HINT_FILETYPE</item>
    </dictionary>
  </item>
  <item type="dictionary">
    <dictionary>
      <item key="eng">Hint: Select multiple entries by holding cmd- or Ctrl-key.</item>
      <item key="fra">Hint: Select multiple entries by holding cmd- or Ctrl-key.</item>
      <item key="ger">Tipp: Sie können mehrere Einträge durch das Halten der cmd- bzw. Strg-Taste auswählen.</item>
      <item key="key">zms.formulator.lib.HINT_MULTISELECT</item>
    </dictionary>
  </item>
</list>
